{
  "items": [
    {
      "starter": [
        { "name": "Doran's Shield", "img": "/items/1054.png" },
        { "name": "Doran's Blade", "img": "/items/1055.png" },
        { "name": "Doran's Ring", "img": "/items/1056.png" },
        { "name": "Dark Seal", "img": "/items/1082.png" },
        { "name": "Cull", "img": "/items/1083.png" },
        { "name": "Scorchclaw Pup", "img": "/items/1101.png" },
        { "name": "Gustwalker Hatchling", "img": "/items/1102.png" },
        { "name": "Mosstomper Seedling", "img": "/items/1103.png" },
        { "name": "Guardian's Horn", "img": "/items/2051.png" },
        { "name": "Tear of the Goddess", "img": "/items/3070.png" },
        { "name": "Kalista's Black Spear", "img": "/items/3599.png" },
        { "name": "Spellthief's Edge", "img": "/items/3850.png" },
        { "name": "Steel Shoulderguards", "img": "/items/3854.png" },
        { "name": "Relic Shield", "img": "/items/3858.png" },
        { "name": "Spectral Sickle", "img": "/items/3862.png" },
        { "name": "Guardian's Hammer", "img": "/items/3184.png" },
        { "name": "Guardian's Blade", "img": "/items/3177.png" },
        { "name": "Guardian's Orb", "img": "/items/3112.png" }
      ],
      "consumable": [
        { "name": "Health Potion", "img": "/items/2003.png" },
        { "name": "Refillable Potion", "img": "/items/2031.png" },
        { "name": "Corrupting Potion", "img": "/items/2033.png" },
        { "name": "Control Ward", "img": "/items/2055.png" },
        { "name": "Elixir of Iron", "img": "/items/2138.png" },
        { "name": "Elixir of Sorcery", "img": "/items/2139.png" },
        { "name": "Elixir of Wrath", "img": "/items/2140.png" }
      ],
      "trinkets": [
        { "name": "Stealth Ward", "img": "/items/3340.png" },
        { "name": "Farsight Alteration", "img": "/items/3363.png" },
        { "name": "Oracle Lens", "img": "/items/3364.png" }
      ],
      "distributed": [
        { "name": "Total Biscuit of Everlasting Will", "img": "/items/2010.png" },
        { "name": "Poro-Snax", "img": "/items/2052.png" },
        { "name": "Minion Dematerializer", "img": "/items/2403.png" },
        { "name": "Commencing Stopwatch", "img": "/items/2419.png" },
        { "name": "Slightly Magical Footwear", "img": "/items/2422.png" },
        { "name": "Your Cut", "img": "/items/3400.png" },
        { "name": "Eye of the Herald", "img": "/items/3513.png" },
        { "name": "Perfectly Timed Stopwatch", "img": "/items/2419.png" }
      ],
      "boots": [
        { "name": "Boots", "img": "/items/1001.png" },
        { "name": "Berserker's Greaves", "img": "/items/3006.png" },
        { "name": "Boots of Swiftness", "img": "/items/3009.png" },
        { "name": "Sorcerer's Shoes", "img": "/items/3020.png" },
        { "name": "Plated Steelcaps", "img": "/items/3047.png" },
        { "name": "Mercury's Treads", "img": "/items/3111.png" },
        { "name": "Mobility Boots", "img": "/items/3117.png" },
        { "name": "Ionian Boots of Lucidity", "img": "/items/3158.png" }
      ],
      "basic": [
        { "name": "Faerie Charm", "img": "/items/1004.png" },
        { "name": "Rejuvenation Bead", "img": "/items/1006.png" },
        { "name": "Cloak of Aligity", "img": "/items/1018.png" },
        { "name": "Blasting Wand", "img": "/items/1026.png" },
        { "name": "Sapphire Crystal", "img": "/items/1027.png" },
        { "name": "Ruby Crystal", "img": "/items/1028.png" },
        { "name": "Cloth Armor", "img": "/items/1029.png" },
        { "name": "Null-Magic Mantle", "img": "/items/1033.png" },
        { "name": "Long Sword", "img": "/items/1036.png" },
        { "name": "Pickaxe", "img": "/items/1037.png" },
        { "name": "B.F. Sword", "img": "/items/1038.png" },
        { "name": "Dagger", "img": "/items/1042.png" },
        { "name": "Amplifying Tome", "img": "/items/1052.png" },
        { "name": "Needlessly Large Rod", "img": "/items/1058.png" },
        { "name": "Sheen", "img": "/items/3057.png" },
        { "name": "Stopwatch", "img": "/items/2419.png" }
      ],
      "epic": [
        { "name": "Giant's Belt", "img": "/items/1011.png" },
        { "name": "Chain Vest", "img": "/items/1031.png" },
        { "name": "Recurve Bow", "img": "/items/1043.png" },
        { "name": "Vampiric Scepter", "img": "/items/1053.png" },
        { "name": "Negatron Cloak", "img": "/items/1057.png" },
        { "name": "Kircheis Shard", "img": "/items/2015.png" },
        { "name": "Glacial Buckler", "img": "/items/3024.png" },
        { "name": "Last Whisper", "img": "/items/3035.png" },
        { "name": "Hearthbound Axe", "img": "/items/3051.png" },
        { "name": "Winged Moonplate", "img": "/items/3066.png" },
        { "name": "Kindlegem", "img": "/items/3067.png" },
        { "name": "Bramble Vest", "img": "/items/3076.png" },
        { "name": "Tiamat", "img": "/items/3077.png" },
        { "name": "Warden's Mail", "img": "/items/3082.png" },
        { "name": "Ironspike Whip", "img": "/items/6029.png" },
        { "name": "Bami's Cinder", "img": "/items/6660.png" },
        { "name": "Rageknife", "img": "/items/6677.png" },
        { "name": "Phage", "img": "/items/3044.png" },
        { "name": "Noonquiver", "img": "/items/6670.png" },
        { "name": "Bandleglass Mirror", "img": "/items/4642.png" },
        { "name": "Watchful Wardstone", "img": "/items/4638.png" },
        { "name": "Leeching Leer", "img": "/items/4635.png" },
        { "name": "Verdant Barrier", "img": "/items/4632.png" },
        { "name": "Blighting Jewel", "img": "/items/4630.png" },
        { "name": "Oblivion Orb", "img": "/items/3916.png" },
        { "name": "Harrowing Crescent", "img": "/items/3863.png" },
        { "name": "Targon's Buckler", "img": "/items/3859.png" },
        { "name": "Runesteel Spaulders", "img": "/items/3855.png" },
        { "name": "Frostfang", "img": "/items/3851.png" },
        { "name": "Catalyst of Aeons", "img": "/items/3803.png" },
        { "name": "Lost Chapter", "img": "/items/3802.png" },
        { "name": "Crystalline Bracer", "img": "/items/3801.png" },
        { "name": "Spectre's Cowl", "img": "/items/3211.png" },
        { "name": "Seeker's Armguard", "img": "/items/3191.png" },
        { "name": "Hexdrinker", "img": "/items/3155.png" },
        { "name": "Hextech Alternator", "img": "/items/3145.png" },
        { "name": "Quicksilver Sash", "img": "/items/3140.png" },
        { "name": "Serrated Dirk", "img": "/items/3134.png" },
        { "name": "Caulfield's Warhammer", "img": "/items/3133.png" },
        { "name": "Executioner's Calling", "img": "/items/3123.png" },
        { "name": "Forbidden Idol", "img": "/items/3114.png" },
        { "name": "Aether Wisp", "img": "/items/3113.png" },
        { "name": "Fiendish Codex", "img": "/items/3108.png" },
        { "name": "Aegis of the Legion", "img": "/items/3105.png" },
        { "name": "Zeal", "img": "/items/3086.png" }
      ],
      "legendary": [
        { "name": "Archangel's Staff", "img": "/items/3003.png" },
        { "name": "Manamune", "img": "/items/3004.png" },
        { "name": "Chemtech Purifier", "img": "/items/3011.png" },
        { "name": "Guardian Angel", "img": "/items/3026.png" },
        { "name": "Infinity Edge", "img": "/items/3031.png" },
        { "name": "Mortal Reminder", "img": "/items/3033.png" },
        { "name": "Lord Dominik's Regards", "img": "/items/3036.png" },
        { "name": "Seraph's Embrace", "img": "/items/3040.png" },
        { "name": "Mejai's Soulstealer", "img": "/items/3041.png" },
        { "name": "Muramana", "img": "/items/3042.png" },
        { "name": "Anathema's Chains", "img": "/items/8001.png" },
        { "name": "Abyssal Mask", "img": "/items/8020.png" },
        { "name": "Phantom Dancer", "img": "/items/3046.png" },
        { "name": "Zeke's Convergence", "img": "/items/3050.png" },
        { "name": "Sterak's Gage", "img": "/items/3053.png" },
        { "name": "Spirit Visage", "img": "/items/3065.png" },
        { "name": "Sunfire Aegis", "img": "/items/3068.png" },
        { "name": "Black Cleaver", "img": "/items/3071.png" },
        { "name": "Bloodthirster", "img": "/items/3072.png" },
        { "name": "Ravenous Hydra", "img": "/items/3074.png" },
        { "name": "Thornmail", "img": "/items/3075.png" },
        { "name": "Rabadon's Deathcap", "img": "/items/3089.png" },
        { "name": "Navori Quickblades", "img": "/items/6675.png" },
        { "name": "The Collector", "img": "/items/6676.png" },
        { "name": "Serylda's Grudge", "img": "/items/6694.png" },
        { "name": "Serpent's Fang", "img": "/items/6695.png" },
        { "name": "Axiom Arc", "img": "/items/6696.png" },
        { "name": "Turbo Chemtank", "img": "/items/6664.png" },
        { "name": "Staff of Flowing Water", "img": "/items/6616.png" },
        { "name": "Chempunk Chainsword", "img": "/items/6609.png" },
        { "name": "Death's Dance", "img": "/items/6333.png" },
        { "name": "Silvermere Dawn", "img": "/items/6035.png" },
        { "name": "Shadowflame", "img": "/items/4645.png" },
        { "name": "Demonic Embrace", "img": "/items/4637.png" },
        { "name": "Cosmic Drive", "img": "/items/4629.png" },
        { "name": "Horizon Focus", "img": "/items/4628.png" },
        { "name": "Force of Nature", "img": "/items/4401.png" },
        { "name": "Black Mist Scythe", "img": "/items/3864.png" },
        { "name": "Bulwark of the Mountain", "img": "/items/3860.png" },
        { "name": "Pauldrons of Whiterock", "img": "/items/3857.png" },
        { "name": "Shard of True Ice", "img": "/items/3853.png" },
        { "name": "Edge of Night", "img": "/items/3814.png" },
        { "name": "Titanic Hydra", "img": "/items/3748.png" },
        { "name": "Dead Man's Plate", "img": "/items/3742.png" },
        { "name": "Essence Reaver", "img": "/items/3508.png" },
        { "name": "Ardent Censer", "img": "/items/3504.png" },
        { "name": "Mikael's Blessing", "img": "/items/3222.png" },
        { "name": "Gargoyle Stoneplate", "img": "/items/3193.png" },
        { "name": "Hullbreaker", "img": "/items/3181.png" },
        { "name": "Umbral Glaive", "img": "/items/3179.png" },
        { "name": "Morellonomicon", "img": "/items/3165.png" },
        { "name": "Spear Of Shojin", "img": "/items/3161.png" },
        { "name": "Zhonya's Hourglass", "img": "/items/3157.png" },
        { "name": "Maw of Malmortius", "img": "/items/3156.png" },
        { "name": "Blade of The Ruined King", "img": "/items/3153.png" },
        { "name": "Randuin's Omen", "img": "/items/3143.png" },
        { "name": "Youmuu's Ghostblade", "img": "/items/3142.png" },
        { "name": "Mercurial Scimitar", "img": "/items/3139.png" },
        { "name": "Void Staff", "img": "/items/3135.png" },
        { "name": "Guinsoo's Rageblade", "img": "/items/3124.png" },
        { "name": "Fimbulwinter", "img": "/items/3121.png" },
        { "name": "Winter's Approach", "img": "/items/3119.png" },
        { "name": "Rylai's Crystal Scepter", "img": "/items/3116.png" },
        { "name": "Nashor's Tooth", "img": "/items/3115.png" },
        { "name": "Frozen Heart", "img": "/items/3110.png" },
        { "name": "Knight's Vow", "img": "/items/3109.png" },
        { "name": "Redemption", "img": "/items/3107.png" },
        { "name": "Banshee's Veil", "img": "/items/3102.png" },
        { "name": "Lich Bane", "img": "/items/3100.png" },
        { "name": "Stormrazor", "img": "/items/3095.png" },
        { "name": "Rapid Firecannon", "img": "/items/3094.png" },
        { "name": "Wit's End", "img": "/items/3091.png" },
        { "name": "Runaan's Hurricane", "img": "/items/3085.png" },
        { "name": "Warmog's Armor", "img": "/items/3083.png" }
      ],
      "mythic": [
        { "name": "Shurelya's Battlesong", "img": "/items/2065.png" },
        { "name": "Evenshroud", "img": "/items/3001.png" },
        { "name": "Trinity Force", "img": "/items/3078.png" },
        { "name": "Prowler's Claw", "img": "/items/6693.png" },
        { "name": "Eclipse", "img": "/items/6692.png" },
        { "name": "Duskblade of Draktharr", "img": "/items/6691.png" },
        { "name": "Immortal Shieldbow", "img": "/items/6673.png" },
        { "name": "Kraken Slayer", "img": "/items/6672.png" },
        { "name": "Galeforce", "img": "/items/6671.png" },
        { "name": "Radiant Virtue", "img": "/items/6667.png" },
        { "name": "Jak'Sho, The Protean", "img": "/items/6665.png" },
        { "name": "Iceborn Gauntlet", "img": "/items/6662.png" },
        { "name": "Rod of Ages", "img": "/items/6657.png" },
        { "name": "Everfrost", "img": "/items/6656.png" },
        { "name": "Luden's Tempest", "img": "/items/6655.png" },
        { "name": "Liandry's Anguish", "img": "/items/6653.png" },
        { "name": "Divine Sunderer", "img": "/items/6632.png" },
        { "name": "Stridebreaker", "img": "/items/6631.png" },
        { "name": "Goredrinker", "img": "/items/6630.png" },
        { "name": "Moonstone Renewer", "img": "/items/6617.png" },
        { "name": "Crown of the Shattered Queen", "img": "/items/4644.png" },
        { "name": "Night Harvester", "img": "/items/4636.png" },
        { "name": "Riftmaker", "img": "/items/4633.png" },
        { "name": "Imperial Mandate", "img": "/items/4005.png" },
        { "name": "Locket of the Iron Solari", "img": "/items/3190.png" },
        { "name": "Hextech Rocketbelt", "img": "/items/3152.png" },
        { "name": "Heartsteel", "img": "/items/3084.png" }
      ]
    }
  ]
}